NOTICE
onemodel/__init__.py
onemodel/__main__.py
onemodel/builtin_functions.py
onemodel/dsl/__init__.py
onemodel/dsl/onemodel.ebnf
onemodel/dsl/onemodel_walker.py
onemodel/dsl/repl.py
onemodel/namespace.py
onemodel/objects/__init__.py
onemodel/objects/algebraic_rule.py
onemodel/objects/assignment_rule.py
onemodel/objects/base_function.py
onemodel/objects/builtin_function.py
onemodel/objects/function.py
onemodel/objects/model.py
onemodel/objects/module.py
onemodel/objects/object.py
onemodel/objects/parameter.py
onemodel/objects/rate_rule.py
onemodel/objects/reaction.py
onemodel/objects/species.py
onemodel/onemodel.ebnf
onemodel/onemodel.py
onemodel/onemodel_walker.py
onemodel/package_manager.py
onemodel/repl.py
onemodel/scope.py
onemodel/utils/__init__.py
onemodel/utils/check.py
onemodel/utils/get_ast_names.py
onemodel/utils/math_2_fullname.py
onemodel-1.0.0.dist-info/entry_points.txt
onemodel-1.0.0.dist-info/LICENSE
onemodel-1.0.0.dist-info/WHEEL
onemodel-1.0.0.dist-info/METADATA
onemodel-1.0.0.dist-info/RECORD
