Metadata-Version: 2.1
Name: onemodel
Version: 1.0.0
Summary: OneModel: an open-source SBML modeling tool
Home-page: https://github.com/sb2cl/onemodel
License: Apache-2.0
Author: Fernando N. Santos-Navarro
Author-email: fersann1@upv.es
Requires-Python: >=3.7,<4.0
Classifier: Development Status :: 3 - Alpha
Classifier: Intended Audience :: Science/Research
Classifier: License :: OSI Approved :: Apache Software License
Classifier: Operating System :: OS Independent
Classifier: Programming Language :: Python
Classifier: Programming Language :: Python :: 3
Classifier: Programming Language :: Python :: 3 :: Only
Classifier: Programming Language :: Python :: 3.10
Classifier: Programming Language :: Python :: 3.7
Classifier: Programming Language :: Python :: 3.8
Classifier: Programming Language :: Python :: 3.9
Classifier: Topic :: Scientific/Engineering :: Bio-Informatics
Requires-Dist: GitPython (>=3.1.20,<4.0.0)
Requires-Dist: importlib-resources
Requires-Dist: python-libsbml (==5.19.2)
Requires-Dist: tabulate (>=0.9.0,<0.10.0)
Requires-Dist: tatsu (==4.4.0)
Requires-Dist: tomli
Project-URL: Repository, https://github.com/sb2cl/onemodel
